DySymNet/SymbolicRegression.py
DySymNet/__init__.py
DySymNet/scripts/__init__.py
DySymNet/scripts/controller.py
DySymNet/scripts/functions.py
DySymNet/scripts/params.py
DySymNet/scripts/pretty_print.py
DySymNet/scripts/regularization.py
DySymNet/scripts/symbolic_network.py
DySymNet/scripts/utils.py
DySymNet-0.2.0.dist-info/LICENSE
DySymNet-0.2.0.dist-info/METADATA
DySymNet-0.2.0.dist-info/WHEEL
DySymNet-0.2.0.dist-info/top_level.txt
DySymNet-0.2.0.dist-info/RECORD
