Metadata-Version: 2.1
Name: DySymNet
Version: 0.2.0
Summary: This package contains the official Pytorch implementation for the paper "A Neural-Guided Dynamic Symbolic Network for Exploring Mathematical Expressions from Data" accepted by ICML'24.
Home-page: https://github.com/AILWQ/DySymNet
Author: Wenqiang Li
Author-email: liwenqiang2021@gmail.com
License: MIT
Platform: UNKNOWN
Classifier: Programming Language :: Python :: 3
Classifier: License :: OSI Approved :: MIT License
Classifier: Operating System :: OS Independent
Requires-Python: >=3.6.0
License-File: LICENSE
Requires-Dist: scikit-learn (==1.5.2)
Requires-Dist: numpy (==1.26.4)
Requires-Dist: sympy (==1.13.3)
Requires-Dist: torch (==2.2.2)
Requires-Dist: matplotlib (==3.9.2)
Requires-Dist: tqdm (==4.66.5)
Requires-Dist: pandas (==2.2.3)
Requires-Dist: pip (==24.2)
Requires-Dist: scipy (==1.13.1)
